{
    "titulo": "Caiolo",
    "Coordenadas": "46° 09′ N, 9° 48′ L",
    "País": "Itália",
    "Região": "Lombardia",
    "Província": "Sondrio",
    "Área total": "33 km²",
    "População total": "956 hab.",
    "Densidade": "29 hab./km²",
    "Altitude": "335 m",
    "Comunas limítrofes": "Albosaggia , Carona (BG), Castione Andevenno , Cedrasco , Foppolo (BG), Piateda , Postalesio , Sondrio",
    "Código, ISTAT": "014011",
    "Código cadastral": "B366",
    "Código postal": "23010",
    "Prefixo telefônico": "0342",
    "Sítio": "www.comune.caiolo.so.it"
}