{
    "titulo": "Cérbero",
    "Nome nativo": "Κέρβερος",
    "Morada": "Hades",
    "Cônjuge(s)": "Quimera",
    "Pais": "Tifão e Equidna",
    "Irmão(s)": [
        "Ortros[1][2][3]",
        "Hidra de Lerna[4][5]",
        "Quimera[6][7][8][9]",
        "Ladão ou Dragão das Hespérides[10][11]",
        "Ethon ou Águia do Cáucaso[10][12]",
        "Esfinge[13][9][14]",
        "Faia ou a Porca de Cromíon[15]",
        "Gorgon Aix[11]",
        "Dragão da Cólquida[9]",
        "Cila[9]",
        "Hidra de Lerna[16]",
        "Equidnades[17]",
        "Leão de Nemeia[18]",
        "Dragão da Cólquida, como filho de Gaia e Tifão[19]",
        "Drakones Troiades, As Duas Serpentes Marinhas que mataram Laocoonte e seus filhos[20]",
        "Anemoi Thuellai, os ventos destrutivos da tempestade, filhos de Tifão. Eles foram mantidos trancados dentro da ilha flutuante de Eólia e liberados sob o comando dos deuses para causar seu caos.[21]",
        "Harpias[22]"
    ]
}