{
    "titulo": "Kate Grigorieva",
    "Nome completo": "Ekaterina Sergeyevna Grigorieva",
    "Nascimento": "15 de setembro de 1988 (36 anos) Olenegorsk , União Soviética",
    "Nacionalidade": "russa",
    "Ocupação": "Modelo",
    "Principais trabalhos": "Victoria's Secret",
    "Altura": "1,80 m",
    "Cor do cabelo": "Louro escuro",
    "Cor dos olhos": "Verdes",
    "Medidas": "83-61-89 cm",
    "Manequim": "34",
    "Calçado": "38.5 UE / 8 US",
    "Agência": "Oui Management Paris, The Lions NY, RF Model Management"
}