{
    "titulo": "Lopo de Brito",
    "Antecessor(a)": "João da Silveira",
    "Sucessor(a)": "Fernão Gomes de Lemos",
    "Nascimento": "c. 1480",
    "Morte": "c. 1547 (67 anos)",
    "Descendência": "Iria de Brito, Condessa de Atalaia (neta) Bárbara Micaela de Ataíde (trineta)",
    "Pai": "João de Brito Nogueira",
    "Mãe": "D. Brites de Lima",
    "Irmão(ã)": "Jorge de Brito, capitão das Molucas",
    "Ocupação": "Fidalgo , Militar",
    "Filho(s)": "João de Brito, Cristóvão de Brito",
    "Filha(s)": "Francisca de Brito, Inês de Brito, Guiomar de Brito",
    "Religião": "Católica"
}