{
    "titulo": "Pedro V",
    "Reinado": "15 de novembro de 1853 a 11 de novembro de 1861",
    "Aclamação": "16 de setembro de 1855",
    "Predecessores": "Maria II",
    "Sucessor(a)": "Carlos I de Portugal",
    "Regente": "Fernando II (1853–1855)",
    "Predecessor(a)": "Pedro IV de Portugal",
    "Nascimento": "16 de setembro de 1837 Palácio das Necessidades , Lisboa , Portugal",
    "Morte": "11 de novembro de 1861 (24 anos) Palácio das Necessidades, Lisboa, Portugal",
    "Sepultado em": "Panteão da Dinastia de Bragança , Igreja de São Vicente de Fora , Lisboa, Portugal",
    "Nome completo": "",
    "Esposa": "Estefânia de Hohenzollern-Sigmaringen",
    "Casa": "Bragança",
    "Pai": "Fernando II de Portugal",
    "Mãe": "Maria II de Portugal",
    "Religião": "Catolicismo",
    "Assinatura": "",
    "Brasão": ""
}