{
    "titulo": "San Rocco al Porto",
    "Coordenadas": "45° 09′ N, 9° 42′ L",
    "País": "Itália",
    "Região": "Lombardia",
    "Província": "Lodi",
    "Área total": "30 km²",
    "População total": "3 249 hab.",
    "Densidade": "108 hab./km²",
    "Altitude": "47 m",
    "Comunas limítrofes": "Fombio , Santo Stefano Lodigiano , Calendasco (PC), Guardamiglio , Piacenza (PC)",
    "Código, ISTAT": "098049",
    "Código cadastral": "I140",
    "Código postal": "26845",
    "Prefixo telefônico": "0377",
    "Padroeiro": "São Roque",
    "Sítio": "www.comune.san-rocco-al-porto.lo.it"
}